Workbook

Sheet Read Me
A1: Bitdoin Academy — Academic Tracking & Career Guidance: MVP Backlog & Requirements Matrix
A2: Companion to: Bitdoin_Academic_Tracking_PRD_v1.0.docx (23 October 2026, draft for owner review)
A4: Sheets
A5: Requirements — Deliverable B: every requirement with epic, phase, priority, dependencies and Given/When/Then acceptance criteria. Filter Phase = 1 and Priority = P0 for the MVP.
A6: WBS & Backlog — work breakdown structure for Phase 0 and Phase 1 (detailed) plus epic placeholders for Phases 2–5. Columns map to Jira/Linear/GitHub Issues fields (Summary, Description, Priority, Labels, Estimate).
A7: Effort Summary — formulas that total the WBS by phase and workstream, with an editable contingency %.
A8: Decisions — open decisions (OD-xx) the owner must make; add the decision and date in the yellow columns.
A9: Risks — prioritised risk register.
A11: How to edit
A12: Yellow cells are inputs: Status, Owner/Assignee, Sprint, Contingency %, and the decision columns. Everything else comes from the PRD; keep IDs stable so cross-references remain valid.
A13: Estimates are ideal person-days. T-shirt sizes: XS 0.5–1, S 1–2, M 3–5, L 6–10, XL 11–15; 'Epic' rows carry roadmap ranges and must be decomposed at phase start.
A14: Priority: P0 must-have for its phase (P0 in Phase 1 = MVP), P1 should-have, P2 could-have, P3 later.
A16: Example row (Requirements): SCORE-006 · Monthly Score Entry · Phase 1 · P0 · Status 'Not started' · Owner 'Backend lead'.

Sheet Requirements
A1: ID | B1: Epic | C1: Phase | D1: Priority | E1: User story | F1: Dependencies | G1: Acceptance criteria (Given/When/Then) | H1: Backend / validation notes | I1: Status | J1: Owner
A2: AUTH-001 | B2: Identity & Access | C2: 1 | D2: P0 | E2: As a signed-in Bitdoin user, I can open Academic Tracking without creating a new account, so that I keep one Bitdoin identity. | F2: Bitdoin identity system (OD-01) | G2: Given a user has a valid Bitdoin session, When they open /academy/scores, Then the module resolves their existing user ID and shows onboarding or dashboard without a second sign-up. Given no session, When they open the route, Then they are redirected to /auth with a return URL and land back on /academy/scores after sign-in. | H2: Module stores only an opaque bitdoin_user_id reference; never copies passwords or auth secrets. | I2: Not started
A3: AUTH-002 | B3: Identity & Access | C3: 1 | D3: P0 | E3: As the platform, every Academic Tracking API call is authorised against the record owner, so that no user can read another student's data by changing an ID. | F3: AUTH-001 | G3: Given user A is authenticated, When A requests GET /students/{B_profile_id}/scores for a profile A neither owns nor has an active guardian grant for, Then the API returns 404 (not 403) and writes an access_denied audit event. Automated IDOR tests cover every route listed in Section 27. | H3: Object-level authorisation enforced server-side in one policy layer; UUIDv7 or random IDs, never sequential. | I3: Not started
A4: AUTH-003 | B4: Identity & Access | C4: 1 | D4: P0 | E4: As a user, my interface language (Lao/English) follows the existing Bitdoin EN/ລາວ setting, so that I do not set it twice. | F4: Existing language toggle (OD-04) | G4: Given the user switched Bitdoin to ລາວ, When they open any Academic Tracking screen, Then all module UI strings render in Lao; switching to EN on any screen persists across Bookstore, Academy and the module. | H4: Read/write the same preference key the platform already uses; confirm storage location with owner. | I4: Not started
A5: AUTH-004 | B5: Identity & Access | C5: 3 | D5: P1 | E5: As the platform, I can assign module roles (student, guardian, admin sub-roles) without changing the core Bitdoin user table, so that existing commerce flows are unaffected. | F5: AUTH-001, ADMIN-001 | G5: Given a Bitdoin user, When a guardian link is approved, Then a guardian relationship row is created in the module schema and the user's core account record is unchanged. Admin roles are granted only by a Super Administrator and every grant is audit-logged. | I5: Not started
A6: PROFILE-001 | B6: Academic Profile | C6: 1 | D6: P0 | E6: As a student, I can create an academic profile in under 2 minutes with only the required fields, so that I can start recording scores quickly. | F6: AUTH-001, ADMIN-003 | G6: Given a new user, When they complete onboarding with display name, grade level, academic year, province and school (or 'school not listed'), Then a student_profile and an enrolment for the current academic year are created. Median completion time in usability testing ≤ 120 s on a mid-range Android device. | H6: Required: display_name, grade_level, academic_year, province, school_id OR school_free_text. Optional: district, goals, interests. Date of birth NOT collected; age band only (see PRIV-002). | I6: Not started
A7: PROFILE-002 | B7: Academic Profile | C7: 1 | D7: P0 | E7: As a student, I can choose my school from a searchable list or enter it as free text when it is not listed, so that I am never blocked. | F7: ADMIN-003 | G7: Given the school is not in the catalogue, When the student types a name and selects 'Use this name', Then the enrolment stores school_free_text, status=unverified_school, and an admin review task is created. Search tolerates Lao and romanised spellings (see Section 23). | I7: Not started
A8: PROFILE-003 | B8: Academic Profile | C8: 1 | D8: P0 | E8: As a student, my current subjects are pre-filled from my grade and school configuration and I can add, remove or rename them, so that the score form matches my score book. | F8: ADMIN-002, PROFILE-001 | G8: Given grade 11 and a school using the default curriculum template, When onboarding reaches 'Your subjects', Then the default subject list for grade 11 is pre-selected; the student can deselect any, add from catalogue, or add a custom subject (max 25 subjects per enrolment). | I8: Not started
A9: PROFILE-004 | B9: Academic Profile | C9: 1 | D9: P0 | E9: As a student, when a new academic year starts I am asked to confirm promotion, repetition or school change, so that history stays accurate. | F9: PROFILE-001 | G9: Given the academic year configured by admin has rolled over, When the student next opens the module, Then a 'New school year' sheet offers: Promoted to grade N+1 / Repeating grade N / Changed school / Left school. The previous enrolment is closed (read-only) and a new enrolment is created; prior scores are never edited or deleted by this action. | I9: Not started
A10: PROFILE-005 | B10: Academic Profile | C10: 1 | D10: P1 | E10: As a student, I can record a school transfer mid-year, so that scores before and after the move are attributed to the right school and grading scale. | F10: PROFILE-004, SCORE-008 | G10: Given a student transfers in January, When they choose 'Changed school' with an effective month, Then the current enrolment ends at the prior month, a new enrolment starts at the effective month with its own grading scale, and charts mark the boundary with a 'school changed' annotation. | I10: Not started
A11: PROFILE-006 | B11: Academic Profile | C11: 1 | D11: P1 | E11: As a student, I can optionally add goals and subjects of interest, so that recommendations reflect what I care about. | F11: PROFILE-001 | G11: Given the optional step, When the student skips it, Then onboarding completes and the step re-appears as a dashboard card at most once per 30 days. Free-text goals are limited to 200 characters and are excluded from any parent view unless the student shares them. | I11: Not started
A12: PROFILE-007 | B12: Academic Profile | C12: 1 | D12: P0 | E12: As a student, I can view and edit my profile and see exactly what data the module holds about me, so that I stay in control. | F12: PROFILE-001, PRIV-004 | G12: Given the profile screen, When the student opens 'My data', Then they see profile fields, number of score records, uploads stored, guardian links and consents, each with edit or delete actions as permitted. | I12: Not started
A13: PROFILE-008 | B13: Academic Profile | C13: 2 | D13: P2 | E13: As a student in a lower-secondary grade, I can use the module with an age-appropriate experience, so that younger students are supported safely. | F13: PRIV-002, OD-07 | G13: Given a student selects a lower-secondary grade, When the age band is below the threshold set by legal review (OD-07), Then guardian consent is required before score data is saved and AI chat is disabled until consent is recorded. | H13: Scope decision: MVP targets Grades 10–12; Grades 6–9 gated by legal review. | I13: Not started
A14: SCORE-001 | B14: Monthly Score Entry | C14: 1 | D14: P0 | E14: As a student, I can enter all subject scores for one reporting period on a single mobile screen, so that monthly entry takes under 90 seconds. | F14: PROFILE-003, ADMIN-002 | G14: Given 8 enrolled subjects on a 0–10 scale, When the student selects a period and types scores using the numeric keypad, Then focus advances to the next subject on 'Next', and a returning user can submit 8 scores in ≤ 90 s (median, usability test). | H14: Numeric keyboard (inputmode=decimal); accepts Lao digits ໐–໙ and normalises to Arabic numerals. | I14: Not started
A15: SCORE-002 | B15: Monthly Score Entry | C15: 1 | D15: P0 | E15: As a student, I select academic year, term/semester and month (reporting period) from lists generated by my school's calendar, so that I cannot record an impossible period. | F15: ADMIN-004 | G15: Given the enrolment's academic calendar defines periods Sep–May, When the student opens the period selector, Then only configured periods for that enrolment appear, the first period without a submitted record is pre-selected, and future periods beyond the current month are disabled. | I15: Not started
A16: SCORE-003 | B16: Monthly Score Entry | C16: 1 | D16: P0 | E16: As a student, the form validates each score against the grading scale, so that typing mistakes are caught immediately. | F16: ADMIN-002 | G16: Given a 0–10 scale with step 0.5, When the student enters 11, 7.3 or 'abc', Then the field shows an inline error ('Score must be between 0 and 10 in steps of 0.5') and Submit is disabled until fixed; 7.5 and 10 are accepted; leading/trailing spaces are trimmed. | I16: Not started
A17: SCORE-004 | B17: Monthly Score Entry | C17: 1 | D17: P0 | E17: As a student, I can mark a subject as 'Not recorded yet', 'Not applicable this period' or 'Absent/exempt', so that missing data is explicit rather than zero. | F17: SCORE-001 | G17: Given a subject has no score, When the student chooses a status, Then the record stores value=NULL with status in {missing, not_applicable, exempt}; NULL values are excluded from averages and never treated as 0; the dashboard shows the count of missing subjects. | I17: Not started
A18: SCORE-005 | B18: Monthly Score Entry | C18: 1 | D18: P0 | E18: As a student, my partially completed entry is saved as a draft automatically, so that I do not lose work when the connection drops. | F18: SCORE-001 | G18: Given the student has typed 3 of 8 scores, When the app goes offline or the tab closes, Then the draft persists locally (IndexedDB) and server-side on the next successful sync; reopening the period restores all typed values. Drafts never contribute to analytics. | I18: Not started
A19: SCORE-006 | B19: Monthly Score Entry | C19: 1 | D19: P0 | E19: As a student, I review a summary and explicitly submit the period, so that only confirmed data is analysed. | F19: SCORE-003 | G19: Given all fields are valid or have a status, When the student taps 'Review' then 'Confirm and save', Then a score_entry is stored with state=submitted, source=manual, verification=self_reported, and the dashboard refreshes within 3 s (p95). | I19: Not started
A20: SCORE-007 | B20: Monthly Score Entry | C20: 1 | D20: P0 | E20: As a student, I can correct a submitted score and the previous value is retained in history, so that corrections are transparent. | F20: SCORE-006 | G20: Given a submitted October Mathematics score of 6, When the student edits it to 7 with an optional reason, Then the current value becomes 7, a score_revision row stores old=6/new=7/actor/timestamp/reason, analytics are recalculated, and 'Edited' appears next to the score with a viewable history. | I20: Not started
A21: SCORE-008 | B21: Monthly Score Entry | C21: 1 | D21: P0 | E21: As the platform, I store each score in its original grading scale together with a scale reference, so that different school scales are never silently mixed. | F21: ADMIN-002 | G21: Given a score of 38/50 under scale S2, When it is saved, Then raw_value=38 and grading_scale_id=S2 are stored; normalised_value=0.76 is derived only when S2.normalisable=true; charts never plot two different scales on one axis without a 'converted to %' label. | I21: Not started
A22: SCORE-009 | B22: Monthly Score Entry | C22: 1 | D22: P0 | E22: As a student, I am prevented from creating two records for the same subject and period, so that duplicates do not distort averages. | F22: SCORE-006 | G22: Given October Mathematics already exists for the enrolment, When the student starts a new entry for October, Then the existing values open in edit mode; the database enforces UNIQUE(enrolment_id, reporting_period_id, subject_enrolment_id) on current records; an API request that would duplicate returns 409 SCORE_DUPLICATE. | I22: Not started
A23: SCORE-010 | B23: Monthly Score Entry | C23: 1 | D23: P0 | E23: As a student, I can browse my complete score history by year, period and subject, so that I can review past results. | F23: SCORE-006 | G23: Given 2 academic years of data, When the student opens History, Then entries are grouped by academic year > term > period, each showing subject scores, source (manual/photo), verification state and edit marker; closed enrolments are read-only. | I23: Not started
A24: SCORE-011 | B24: Monthly Score Entry | C24: 1 | D24: P1 | E24: As a student, I can see term and annual summaries computed from my monthly scores or entered directly when my school issues an official term result, so that both views are available. | F24: SCORE-006, ANALYSIS-001 | G24: Given monthly scores exist for Sep–Dec, When the term ends, Then a computed term mean is displayed and labelled 'Calculated by Bitdoin'; if the student enters an official term score, it is stored as period_type=term_official and shown separately; computed and official values are never overwritten by each other. | I24: Not started
A25: SCORE-012 | B25: Monthly Score Entry | C25: 1 | D25: P0 | E25: As a user, every score shows its data source and verification status, so that self-reported and verified data are always distinguishable. | F25: SCORE-006 | G25: Given any score in any view (dashboard, report, parent view, API), Then it carries source ∈ {manual, ocr_confirmed, school_import} and verification ∈ {self_reported, guardian_acknowledged, school_verified}; MVP only creates self_reported; UI shows a badge for anything other than self_reported. | I25: Not started
A26: SCORE-013 | B26: Monthly Score Entry | C26: 1 | D26: P1 | E26: As a student, I can add a subject mid-year or drop one, so that the form adapts when my timetable changes. | F26: PROFILE-003 | G26: Given a subject is dropped from November, When the student removes it, Then subject_enrolment.end_period is set; earlier scores remain; the subject no longer appears in new periods; trend charts end at the last recorded period. | I26: Not started
... A141: PRIV-008 | B141: Privacy, Consent & Safety | C141: 2 | D141: P1 | E141: As a user, I can report abuse (wrong guardian link, inappropriate AI output, impersonation) from any screen, so that issues reach support quickly. | F141: ADMIN-005 | G141: Given 'Report a problem', Then categories include guardian link, AI answer, account misuse and other; safety-category reports create a priority ticket with 1 business day first response target. | I141: Not started

Sheet WBS & Backlog
A1: Task ID | B1: Workstream | C1: Phase | D1: Task (summary) | E1: Description | F1: Priority | G1: Dependencies | H1: Size | I1: Est. low (days) | J1: Est. high (days) | K1: Est. mid (days) | L1: Linked requirements | M1: Acceptance criteria | N1: Status | O1: Assignee | P1: Sprint
A2: PM-001 | B2: Product management | C2: 0 Research & validation | D2: Codebase and architecture discovery | E2: Review Bitdoin repository, hosting, auth/session model, database, Academy content model, subscription records and deployment pipeline with the owner; complete the discovery checklist in Section 25.6. | F2: P0 | G2: Owner grants access | H2: M | I2: 3 | J2: 5 | K2: =AVERAGE(I2:J2) -> 4 | L2: OD-01..OD-06 | M2: Discovery checklist complete; architecture option (Section 24.2) selected and recorded in decision register. | N2: Not started
A3: PM-002 | B3: Product management | C3: 0 Research & validation | D3: Owner decision workshop | E3: Run a workshop to close the pre-development decisions in Section 40.2 (scope grades, monetisation packaging, AI provider policy, data residency). | F3: P0 | G3: PM-001 | H3: S | I3: 1 | J3: 2 | K3: =AVERAGE(I3:J3) -> 1.5 | L3: OD-01..OD-16 | M3: Each P0 decision has an owner, a decision and a date in the register. | N3: Not started
A4: RES-001 | B4: Content and research | C4: 0 Research & validation | D4: Score-book sample collection (consented) | E4: Collect 150–300 score-book photos from ≥ 20 schools in ≥ 6 provinces with written student and guardian consent; redact names; store in restricted research bucket. | F4: P0 | G4: LEG-001 | H4: L | I4: 6 | J4: 10 | K4: =AVERAGE(I4:J4) -> 8 | L4: OCR-004 | M4: Sample inventory spreadsheet with school, province, layout type, consent reference; ≥ 150 usable images. | N4: Not started
A5: RES-002 | B5: Content and research | C5: 0 Research & validation | D5: Grading practice survey | E5: Document scales, steps, reporting periods and term/annual rules from the samples and 10+ teacher interviews. | F5: P0 | G5: RES-001 | H5: M | I5: 3 | J5: 5 | K5: =AVERAGE(I5:J5) -> 4 | L5: SCORE-003, SCORE-008, ADMIN-002 | M5: Grading configuration catalogue with ≥ 1 verified template per school type; unknowns listed. | N5: Not started
A6: RES-003 | B6: Content and research | C6: 0 Research & validation | D6: Student and parent interviews | E6: 12–20 student and 8–12 parent interviews plus a 5-minute value survey (n ≥ 100) on willingness to record scores and pay for insights. | F6: P0 | G6: — | H6: M | I6: 3 | J6: 5 | K6: =AVERAGE(I6:J6) -> 4 | L6: — | M6: Synthesis report with top needs, objections and price-sensitivity ranges. | N6: Not started
A7: RES-004 | B7: Content and research | C7: 0 Research & validation | D7: Concierge validation | E7: Run a manual pilot: 30–50 students submit scores via form; team returns a hand-built monthly summary; test 2 price points via QR payment. | F7: P1 | G7: RES-003 | H7: M | I7: 3 | J7: 5 | K7: =AVERAGE(I7:J7) -> 4 | L7: — | M7: Retention to 2nd month and paid conversion measured; go/no-go recorded. | N7: Not started
A8: LEG-001 | B8: Security | C8: 0 Research & validation | D8: Lao legal review | E8: Engage Lao counsel on Law No. 25/NA, consent for minors, cross-border transfer, AI vendor processing, retention, and the expected new data protection law. | F8: P0 | G8: — | H8: M | I8: 3 | J8: 5 | K8: =AVERAGE(I8:J8) -> 4 | L8: PRIV-001..PRIV-006 | M8: Written opinion answering the questions in Section 29.2; OD-07 closed. | N8: Not started
A9: AI-RES-001 | B9: OCR/AI | C9: 0 Research & validation | D9: OCR feasibility benchmark | E9: Evaluate 2–3 vision-language models and 1 conventional OCR engine on 100 labelled samples for field accuracy, latency and cost. | F9: P0 | G9: RES-001 | H9: M | I9: 3 | J9: 5 | K9: =AVERAGE(I9:J9) -> 4 | L9: OCR-004, AI-010 | M9: Benchmark report with per-field accuracy, cost per page and recommendation (Section 21.3). | N9: Not started
A10: UX-001 | B10: UX/UI | C10: 1 Core MVP | D10: Design tokens and component mapping | E10: Map module components to existing Bitdoin styles (theme colour #1e3a5f, typography, buttons); define Lao typography rules. | F10: P0 | G10: PM-001 | H10: S | I10: 1 | J10: 2 | K10: =AVERAGE(I10:J10) -> 1.5 | L10: AUTH-003 | M10: Token sheet approved; Lao/EN sample screens pass visual review. | N10: Not started
A11: UX-002 | B11: UX/UI | C11: 1 Core MVP | D11: Onboarding and profile flows | E11: High-fidelity mobile + desktop designs for screens 1–3 and 23. | F11: P0 | G11: UX-001 | H11: M | I11: 3 | J11: 5 | K11: =AVERAGE(I11:J11) -> 4 | L11: PROFILE-001..007, PRIV-001 | M11: Prototype tested with 5 students; median onboarding ≤ 120 s. | N11: Not started
A12: UX-003 | B12: UX/UI | C12: 1 Core MVP | D12: Score entry and history | E12: Designs for screens 5 and 22 incl. draft, validation, missing-status and correction states. | F12: P0 | G12: UX-001 | H12: M | I12: 3 | J12: 5 | K12: =AVERAGE(I12:J12) -> 4 | L12: SCORE-001..013 | M12: Prototype test: returning user enters 8 scores ≤ 90 s. | N12: Not started
A13: UX-004 | B13: UX/UI | C13: 1 Core MVP | D13: Dashboard and charts | E13: Designs for screen 4 and per-subject view; chart specs incl. accessible tables. | F13: P0 | G13: UX-001 | H13: M | I13: 3 | J13: 5 | K13: =AVERAGE(I13:J13) -> 4 | L13: DASH-001..008 | M13: Charts reviewed against Section 18 specs and WCAG 2.2 AA contrast. | N13: Not started
... A56: P5-EXAM | B56: Content and research | C56: 5 Exams & ecosystem | D56: Mock exams and ecosystem | E56: Mock exams to verified blueprints, Bookstore recommendations, teacher tools discovery. | F56: P2 | G56: Phase 4 | H56: Epic | I56: 80 | J56: 150 | K56: =AVERAGE(I56:J56) -> 115 | L56: EXAM-001..003, LEARN-006 | M56: Content licensing register complete; blueprint verified for the current year. | N56: Not started

Sheet Effort Summary
A1: Effort summary (ideal person-days) — formulas reference 'WBS & Backlog'
A3: Contingency % | B3: 0.25 | C3: Assumption: 20–30% recommended in PRD Section 38; edit to test scenarios.
A5: Phase | B5: Tasks | C5: Low | D5: High | E5: Mid | F5: High incl. contingency
A6: 0 Research & validation | B6: =COUNTIF('WBS & Backlog'!$C$2:$C$56,A6) -> 8 | C6: =SUMIF('WBS & Backlog'!$C$2:$C$56,A6,'WBS & Backlog'!$I$2:$I$56) -> 25 | D6: =SUMIF('WBS & Backlog'!$C$2:$C$56,A6,'WBS & Backlog'!$J$2:$J$56) -> 42 | E6: =SUMIF('WBS & Backlog'!$C$2:$C$56,A6,'WBS & Backlog'!$K$2:$K$56) -> 33.5 | F6: =D6*(1+$B$3) -> 52.5
A7: 1 Core MVP | B7: =COUNTIF('WBS & Backlog'!$C$2:$C$56,A7) -> 38 | C7: =SUMIF('WBS & Backlog'!$C$2:$C$56,A7,'WBS & Backlog'!$I$2:$I$56) -> 105 | D7: =SUMIF('WBS & Backlog'!$C$2:$C$56,A7,'WBS & Backlog'!$J$2:$J$56) -> 179 | E7: =SUMIF('WBS & Backlog'!$C$2:$C$56,A7,'WBS & Backlog'!$K$2:$K$56) -> 142 | F7: =D7*(1+$B$3) -> 223.75
A8: 2 OCR & analysis | B8: =COUNTIF('WBS & Backlog'!$C$2:$C$56,A8) -> 3 | C8: =SUMIF('WBS & Backlog'!$C$2:$C$56,A8,'WBS & Backlog'!$I$2:$I$56) -> 70 | D8: =SUMIF('WBS & Backlog'!$C$2:$C$56,A8,'WBS & Backlog'!$J$2:$J$56) -> 120 | E8: =SUMIF('WBS & Backlog'!$C$2:$C$56,A8,'WBS & Backlog'!$K$2:$K$56) -> 95 | F8: =D8*(1+$B$3) -> 150
A9: 3 Parent, AI & premium | B9: =COUNTIF('WBS & Backlog'!$C$2:$C$56,A9) -> 4 | C9: =SUMIF('WBS & Backlog'!$C$2:$C$56,A9,'WBS & Backlog'!$I$2:$I$56) -> 90 | D9: =SUMIF('WBS & Backlog'!$C$2:$C$56,A9,'WBS & Backlog'!$J$2:$J$56) -> 150 | E9: =SUMIF('WBS & Backlog'!$C$2:$C$56,A9,'WBS & Backlog'!$K$2:$K$56) -> 120 | F9: =D9*(1+$B$3) -> 187.5
A10: 4 Career guidance | B10: =COUNTIF('WBS & Backlog'!$C$2:$C$56,A10) -> 1 | C10: =SUMIF('WBS & Backlog'!$C$2:$C$56,A10,'WBS & Backlog'!$I$2:$I$56) -> 60 | D10: =SUMIF('WBS & Backlog'!$C$2:$C$56,A10,'WBS & Backlog'!$J$2:$J$56) -> 100 | E10: =SUMIF('WBS & Backlog'!$C$2:$C$56,A10,'WBS & Backlog'!$K$2:$K$56) -> 80 | F10: =D10*(1+$B$3) -> 125
A11: 5 Exams & ecosystem | B11: =COUNTIF('WBS & Backlog'!$C$2:$C$56,A11) -> 1 | C11: =SUMIF('WBS & Backlog'!$C$2:$C$56,A11,'WBS & Backlog'!$I$2:$I$56) -> 80 | D11: =SUMIF('WBS & Backlog'!$C$2:$C$56,A11,'WBS & Backlog'!$J$2:$J$56) -> 150 | E11: =SUMIF('WBS & Backlog'!$C$2:$C$56,A11,'WBS & Backlog'!$K$2:$K$56) -> 115 | F11: =D11*(1+$B$3) -> 187.5
A12: Total | B12: =SUM(B6:B11) -> 55 | C12: =SUM(C6:C11) -> 430 | D12: =SUM(D6:D11) -> 741 | E12: =SUM(E6:E11) -> 585.5 | F12: =SUM(F6:F11) -> 926.25
A14: Phase 1 workstream | B14: Tasks | C14: Low | D14: High | E14: Mid | F14: High incl. contingency
A15: Analytics | B15: =COUNTIFS('WBS & Backlog'!$C$2:$C$56,"1 Core MVP",'WBS & Backlog'!$B$2:$B$56,A15) -> 2 | C15: =SUMIFS('WBS & Backlog'!$I$2:$I$56,'WBS & Backlog'!$C$2:$C$56,"1 Core MVP",'WBS & Backlog'!$B$2:$B$56,A15) -> 4 | D15: =SUMIFS('WBS & Backlog'!$J$2:$J$56,'WBS & Backlog'!$C$2:$C$56,"1 Core MVP",'WBS & Backlog'!$B$2:$B$56,A15) -> 7 | E15: =SUMIFS('WBS & Backlog'!$K$2:$K$56,'WBS & Backlog'!$C$2:$C$56,"1 Core MVP",'WBS & Backlog'!$B$2:$B$56,A15) -> 5.5 | F15: =D15*(1+$B$3) -> 8.75
A16: Backend | B16: =COUNTIFS('WBS & Backlog'!$C$2:$C$56,"1 Core MVP",'WBS & Backlog'!$B$2:$B$56,A16) -> 9 | C16: =SUMIFS('WBS & Backlog'!$I$2:$I$56,'WBS & Backlog'!$C$2:$C$56,"1 Core MVP",'WBS & Backlog'!$B$2:$B$56,A16) -> 26 | D16: =SUMIFS('WBS & Backlog'!$J$2:$J$56,'WBS & Backlog'!$C$2:$C$56,"1 Core MVP",'WBS & Backlog'!$B$2:$B$56,A16) -> 44 | E16: =SUMIFS('WBS & Backlog'!$K$2:$K$56,'WBS & Backlog'!$C$2:$C$56,"1 Core MVP",'WBS & Backlog'!$B$2:$B$56,A16) -> 35 | F16: =D16*(1+$B$3) -> 55
A17: Database | B17: =COUNTIFS('WBS & Backlog'!$C$2:$C$56,"1 Core MVP",'WBS & Backlog'!$B$2:$B$56,A17) -> 3 | C17: =SUMIFS('WBS & Backlog'!$I$2:$I$56,'WBS & Backlog'!$C$2:$C$56,"1 Core MVP",'WBS & Backlog'!$B$2:$B$56,A17) -> 10 | D17: =SUMIFS('WBS & Backlog'!$J$2:$J$56,'WBS & Backlog'!$C$2:$C$56,"1 Core MVP",'WBS & Backlog'!$B$2:$B$56,A17) -> 17 | E17: =SUMIFS('WBS & Backlog'!$K$2:$K$56,'WBS & Backlog'!$C$2:$C$56,"1 Core MVP",'WBS & Backlog'!$B$2:$B$56,A17) -> 13.5 | F17: =D17*(1+$B$3) -> 21.25
A18: DevOps | B18: =COUNTIFS('WBS & Backlog'!$C$2:$C$56,"1 Core MVP",'WBS & Backlog'!$B$2:$B$56,A18) -> 3 | C18: =SUMIFS('WBS & Backlog'!$I$2:$I$56,'WBS & Backlog'!$C$2:$C$56,"1 Core MVP",'WBS & Backlog'!$B$2:$B$56,A18) -> 5 | D18: =SUMIFS('WBS & Backlog'!$J$2:$J$56,'WBS & Backlog'!$C$2:$C$56,"1 Core MVP",'WBS & Backlog'!$B$2:$B$56,A18) -> 9 | E18: =SUMIFS('WBS & Backlog'!$K$2:$K$56,'WBS & Backlog'!$C$2:$C$56,"1 Core MVP",'WBS & Backlog'!$B$2:$B$56,A18) -> 7 | F18: =D18*(1+$B$3) -> 11.25
A19: Frontend | B19: =COUNTIFS('WBS & Backlog'!$C$2:$C$56,"1 Core MVP",'WBS & Backlog'!$B$2:$B$56,A19) -> 7 | C19: =SUMIFS('WBS & Backlog'!$I$2:$I$56,'WBS & Backlog'!$C$2:$C$56,"1 Core MVP",'WBS & Backlog'!$B$2:$B$56,A19) -> 27 | D19: =SUMIFS('WBS & Backlog'!$J$2:$J$56,'WBS & Backlog'!$C$2:$C$56,"1 Core MVP",'WBS & Backlog'!$B$2:$B$56,A19) -> 45 | E19: =SUMIFS('WBS & Backlog'!$K$2:$K$56,'WBS & Backlog'!$C$2:$C$56,"1 Core MVP",'WBS & Backlog'!$B$2:$B$56,A19) -> 36 | F19: =D19*(1+$B$3) -> 56.25
A20: QA | B20: =COUNTIFS('WBS & Backlog'!$C$2:$C$56,"1 Core MVP",'WBS & Backlog'!$B$2:$B$56,A20) -> 4 | C20: =SUMIFS('WBS & Backlog'!$I$2:$I$56,'WBS & Backlog'!$C$2:$C$56,"1 Core MVP",'WBS & Backlog'!$B$2:$B$56,A20) -> 13 | D20: =SUMIFS('WBS & Backlog'!$J$2:$J$56,'WBS & Backlog'!$C$2:$C$56,"1 Core MVP",'WBS & Backlog'!$B$2:$B$56,A20) -> 22 | E20: =SUMIFS('WBS & Backlog'!$K$2:$K$56,'WBS & Backlog'!$C$2:$C$56,"1 Core MVP",'WBS & Backlog'!$B$2:$B$56,A20) -> 17.5 | F20: =D20*(1+$B$3) -> 27.5
A21: Release management | B21: =COUNTIFS('WBS & Backlog'!$C$2:$C$56,"1 Core MVP",'WBS & Backlog'!$B$2:$B$56,A21) -> 2 | C21: =SUMIFS('WBS & Backlog'!$I$2:$I$56,'WBS & Backlog'!$C$2:$C$56,"1 Core MVP",'WBS & Backlog'!$B$2:$B$56,A21) -> 2 | D21: =SUMIFS('WBS & Backlog'!$J$2:$J$56,'WBS & Backlog'!$C$2:$C$56,"1 Core MVP",'WBS & Backlog'!$B$2:$B$56,A21) -> 4 | E21: =SUMIFS('WBS & Backlog'!$K$2:$K$56,'WBS & Backlog'!$C$2:$C$56,"1 Core MVP",'WBS & Backlog'!$B$2:$B$56,A21) -> 3 | F21: =D21*(1+$B$3) -> 5
A22: Security | B22: =COUNTIFS('WBS & Backlog'!$C$2:$C$56,"1 Core MVP",'WBS & Backlog'!$B$2:$B$56,A22) -> 2 | C22: =SUMIFS('WBS & Backlog'!$I$2:$I$56,'WBS & Backlog'!$C$2:$C$56,"1 Core MVP",'WBS & Backlog'!$B$2:$B$56,A22) -> 4 | D22: =SUMIFS('WBS & Backlog'!$J$2:$J$56,'WBS & Backlog'!$C$2:$C$56,"1 Core MVP",'WBS & Backlog'!$B$2:$B$56,A22) -> 7 | E22: =SUMIFS('WBS & Backlog'!$K$2:$K$56,'WBS & Backlog'!$C$2:$C$56,"1 Core MVP",'WBS & Backlog'!$B$2:$B$56,A22) -> 5.5 | F22: =D22*(1+$B$3) -> 8.75
A23: UX/UI | B23: =COUNTIFS('WBS & Backlog'!$C$2:$C$56,"1 Core MVP",'WBS & Backlog'!$B$2:$B$56,A23) -> 6 | C23: =SUMIFS('WBS & Backlog'!$I$2:$I$56,'WBS & Backlog'!$C$2:$C$56,"1 Core MVP",'WBS & Backlog'!$B$2:$B$56,A23) -> 14 | D23: =SUMIFS('WBS & Backlog'!$J$2:$J$56,'WBS & Backlog'!$C$2:$C$56,"1 Core MVP",'WBS & Backlog'!$B$2:$B$56,A23) -> 24 | E23: =SUMIFS('WBS & Backlog'!$K$2:$K$56,'WBS & Backlog'!$C$2:$C$56,"1 Core MVP",'WBS & Backlog'!$B$2:$B$56,A23) -> 19 | F23: =D23*(1+$B$3) -> 30

Sheet Decisions
A1: ID | B1: Decision | C1: Options | D1: Recommendation | E1: Needed by | F1: Decision made | G1: Decided by | H1: Date
A2: OD-01 | B2: Grant codebase/infrastructure access; confirm identity model and architecture option | C2: Option 1/2 vs 3 | D2: Option 1/2 (modular monolith) if feasible | E2: Before Phase 1
A3: OD-02 | B3: MVP grade scope and platform | C3: Grades 10–12 web/PWA; include 6–9; native app | D3: Grades 10–12, responsive web/PWA | E3: Before Phase 1
A4: OD-03 | B4: AI/OCR provider policy and data residency | C4: Hosted provider with DPA; regional; self-hosted | D4: Hosted with no-training, minimal retention, consent; revisit after counsel | E4: Before Phase 2
A5: OD-04 | B5: Navigation placement, routes, language storage, digit display | C5: — | D5: "My Scores" in Academy nav; Arabic digits display | E5: Before Phase 1 design
A6: OD-05 | B6: Access to Academy content model and completion events | C6: API / DB read / manual import | D6: Read API or events | E6: Before Phase 2
A7: OD-06 | B7: Bookstore catalogue access for recommendations | C7: API / DB read | D7: Read API; Phase 5 | E7: Before Phase 5
A8: OD-07 | B8: Consent model and age thresholds (after counsel) | C8: Section 29.3 options | D8: Conservative default until opinion | E8: Before Phase 1 launch
A9: OD-08 | B9: AI Coach academic mode vs separate assistant | C9: Extend Coach / embed new | D9: Extend Coach | E9: Before Phase 3
A10: OD-09 | B10: Integrate study tasks with XP & streaks | C10: Yes non-punitive / No | D10: Yes, opt-in, no streak loss | E10: Before Phase 3
A11: OD-10 | B11: Career Explorer data provenance and personalisation | C11: Add sources / hide salary | D11: Add sources; hide unsourced figures in personalised views | E11: Before Phase 4
A12: OD-11 | B12: Packaging and prices; quotas | C12: Inside Premium; add-ons; prices to test | D12: Inside Premium + Family + one-time report; test prices in 30.5 | E12: Before Phase 3
A13: OD-12 | B13: SMS/telco billing/messaging channels | C13: Now / later | D13: Later after cost study | E13: Phase 5
... A21: OD-20 | B21: Staffing for content and pathways reviews | C21: — | D21: 1 education content manager + 2 part-time reviewers | E21: Before Phase 2/4

Sheet Risks
A1: ID | B1: Risk | C1: Category | D1: Likelihood | E1: Impact | F1: Mitigation | G1: Owner | H1: Decision required
A2: R-01 | B2: Incorrect score extraction by OCR | C2: AI/quality | D2: High | E2: High | F2: Mandatory confirmation; confidence highlighting; silent-error gate ≤ 2%; manual entry equal; correction monitoring | G2: AI engineer | H2: Approve OCR release gate (OD-19)
A3: R-02 | B3: Variability in school grading | C3: Domain | D3: High | E3: Medium | F3: Configurable versioned scales; no cross-school comparison; school aliases; educator review | G3: Education content | H3: Default scale & calendar (OD-02)
A4: R-03 | B4: Insufficient academic data (students stop recording) | C4: Product | D4: Medium | E4: High | F4: 90-s entry; reminders; value after 2 months; concierge validation; parent involvement later | G4: PM | H4: Pilot go/no-go thresholds
A5: R-04 | B5: Poor AI Lao-language responses | C5: AI | D5: Medium | E5: High | F5: Native-rater evaluation; templates fallback; simple Lao glossary; AI only after deterministic outputs | G5: AI engineer | H5: Model/provider selection (OD-03)
A6: R-05 | B6: Misleading career recommendations | C6: Ethics | D6: Medium | E6: High | F6: Interests-first, multiple options, no scores-only steering, factors shown, fairness tests, discussion prompts | G6: Career content | H6: Approve methodology (Section 22)
A7: R-06 | B7: Outdated university information | C7: Content | D7: High | E7: Medium | F7: Provenance fields, review_by, expiry alerts, annual refresh, out-of-date labels | G7: Career content | H7: Staffing for reviews (OD-20)
A8: R-07 | B8: Privacy risks involving minors | C8: Legal/safety | D8: Medium | E8: Very high | F8: Legal review; minimisation; consent model; two-sided guardian links; audit; breach plan | G8: Owner | H8: Consent model (OD-07)
A9: R-08 | B9: Low willingness to pay | C9: Commercial | D9: Medium | E9: High | F9: Free core; Premium bundling; career report; price tests; parent-focused value | G9: Commercial | H9: Packaging & prices (OD-11)
A10: R-09 | B10: AI operating cost | C10: Commercial | D10: Medium | E10: Medium | F10: Quotas, caching, cheaper models for simple tasks, budget rule (30.6) | G10: AI engineer | H10: Cost budget
A11: R-10 | B11: Limited content availability | C11: Content | D11: High | E11: Medium | F11: Start with 4 subjects; content-gap tracking; tutor partnerships; Academy reuse | G11: Content | H11: Content investment
A12: R-11 | B12: Difficult integration with existing codebase | C12: Technical | D12: Medium | E12: High | F12: Discovery first; adapters; Option 3 fallback | G12: Architect | H12: Architecture option (OD-01)
... A16: R-15 | B16: Reputational harm from "official-looking" reports | C16: Trust | D16: Low | E16: Medium | F16: "Self-reported" labelling; no school logos | G16: PM | H16: —
